brottsplatskartan/__init__.py
brottsplatskartan-1.0.5.dist-info/LICENSE
brottsplatskartan-1.0.5.dist-info/METADATA
brottsplatskartan-1.0.5.dist-info/WHEEL
brottsplatskartan-1.0.5.dist-info/top_level.txt
brottsplatskartan-1.0.5.dist-info/RECORD
